{
  "designerVersion" : "1.9.57",
  "id" : "answerForm",
  "name" : "answerForm",
  "lastUpdate" : 1568272300026,
  "rows" : [ [ {
    "type" : "container",
    "dimension" : {
      "xs" : 12
    },
    "propertyValues" : { },
    "reference" : "c996992a-4950-4b2f-863a-bda4d412e3f6",
    "hasValidationError" : false,
    "id" : "pbContainer",
    "rows" : [ [ {
      "type" : "component",
      "dimension" : {
        "xs" : 12
      },
      "propertyValues" : {
        "labelHidden" : {
          "type" : "constant",
          "value" : false
        },
        "hidden" : {
          "type" : "constant",
          "value" : false
        },
        "level" : {
          "type" : "constant",
          "value" : "Level 1"
        },
        "cssClasses" : {
          "type" : "constant",
          "value" : ""
        },
        "widgetId" : {
          "type" : "constant",
          "value" : "pbTitle"
        },
        "readOnly" : {
          "type" : "constant",
          "value" : false
        },
        "label" : {
          "type" : "interpolation"
        },
        "text" : {
          "type" : "interpolation",
          "value" : "{{ task.displayName }}"
        },
        "alignment" : {
          "type" : "constant",
          "value" : "center"
        },
        "class" : {
          "type" : "constant",
          "value" : "org.bonitasoft.web.designer.experimental.parametrizedWidget.TitleWidget"
        },
        "dimension" : {
          "type" : "constant",
          "value" : 12
        }
      },
      "reference" : "55657b42-3617-4c4e-b644-9d5be1e80162",
      "hasValidationError" : false,
      "id" : "pbTitle"
    } ], [ {
      "type" : "component",
      "dimension" : {
        "xs" : 12
      },
      "propertyValues" : {
        "labelHidden" : {
          "type" : "constant",
          "value" : true
        },
        "hidden" : {
          "type" : "constant",
          "value" : false
        },
        "cssClasses" : {
          "type" : "constant",
          "value" : ""
        },
        "widgetId" : {
          "type" : "constant",
          "value" : "pbText"
        },
        "readOnly" : {
          "type" : "constant",
          "value" : false
        },
        "label" : {
          "type" : "interpolation"
        },
        "text" : {
          "type" : "interpolation",
          "value" : "{{ task.displayDescription }}"
        },
        "alignment" : {
          "type" : "constant",
          "value" : "left"
        },
        "class" : {
          "type" : "constant",
          "value" : "org.bonitasoft.web.designer.experimental.parametrizedWidget.TextWidget"
        },
        "dimension" : {
          "type" : "constant",
          "value" : 12
        }
      },
      "reference" : "894fe1b8-7fe2-4a9e-a26d-a25d308e5fb0",
      "hasValidationError" : false,
      "id" : "pbText"
    } ] ]
  } ], [ {
    "type" : "formContainer",
    "dimension" : {
      "xs" : 12
    },
    "propertyValues" : { },
    "reference" : "b1e672bf-24a1-44f9-9332-64e0d43ffcc7",
    "hasValidationError" : false,
    "id" : "pbFormContainer",
    "container" : {
      "type" : "container",
      "dimension" : {
        "xs" : 12
      },
      "propertyValues" : { },
      "reference" : "d66398ad-3022-4bfb-8b23-ffd2c3909c7b",
      "hasValidationError" : false,
      "id" : "pbContainer",
      "rows" : [ [ {
        "type" : "component",
        "dimension" : {
          "xs" : 12
        },
        "propertyValues" : {
          "labelHidden" : {
            "type" : "constant",
            "value" : false
          },
          "hidden" : {
            "type" : "constant",
            "value" : false
          },
          "level" : {
            "type" : "constant",
            "value" : "Level 4"
          },
          "cssClasses" : {
            "type" : "constant",
            "value" : ""
          },
          "widgetId" : {
            "type" : "constant",
            "value" : "pbTitle"
          },
          "readOnly" : {
            "type" : "constant",
            "value" : false
          },
          "label" : {
            "type" : "interpolation"
          },
          "text" : {
            "type" : "interpolation",
            "value" : "Claim"
          },
          "alignment" : {
            "type" : "constant",
            "value" : "left"
          },
          "class" : {
            "type" : "constant",
            "value" : "org.bonitasoft.web.designer.experimental.parametrizedWidget.TitleWidget"
          },
          "dimension" : {
            "type" : "constant",
            "value" : 12
          }
        },
        "reference" : "fb12204a-3c29-4821-bc94-0feeac718d48",
        "hasValidationError" : false,
        "id" : "pbTitle"
      } ], [ {
        "type" : "container",
        "dimension" : {
          "xs" : 12
        },
        "propertyValues" : {
          "repeatedCollection" : {
            "type" : "variable",
            "value" : ""
          },
          "labelHidden" : {
            "type" : "constant",
            "value" : false
          },
          "hidden" : {
            "type" : "constant",
            "value" : false
          },
          "cssClasses" : {
            "type" : "constant",
            "value" : ""
          },
          "widgetId" : {
            "type" : "constant"
          },
          "readOnly" : {
            "type" : "constant",
            "value" : false
          },
          "label" : {
            "type" : "interpolation"
          },
          "alignment" : {
            "type" : "constant",
            "value" : "left"
          },
          "class" : {
            "type" : "constant",
            "value" : "org.bonitasoft.web.designer.experimental.parametrizedWidget.WidgetContainer"
          },
          "dimension" : {
            "type" : "constant",
            "value" : 12
          }
        },
        "reference" : "e878ee1d-0cd5-40f6-b6a8-620c102f13d2",
        "hasValidationError" : false,
        "id" : "pbContainer",
        "rows" : [ [ {
          "type" : "component",
          "dimension" : {
            "xs" : 12
          },
          "propertyValues" : {
            "labelHidden" : {
              "type" : "constant",
              "value" : false
            },
            "hidden" : {
              "type" : "expression",
              "value" : "!claim.description"
            },
            "cssClasses" : {
              "type" : "constant",
              "value" : ""
            },
            "widgetId" : {
              "type" : "constant",
              "value" : "pbText"
            },
            "readOnly" : {
              "type" : "constant",
              "value" : false
            },
            "label" : {
              "type" : "interpolation",
              "value" : "Description"
            },
            "text" : {
              "type" : "interpolation",
              "value" : "{{claim.description}}"
            },
            "alignment" : {
              "type" : "constant",
              "value" : "left"
            },
            "class" : {
              "type" : "constant",
              "value" : "org.bonitasoft.web.designer.experimental.parametrizedWidget.TextWidget"
            },
            "dimension" : {
              "type" : "constant",
              "value" : 12
            }
          },
          "reference" : "fec19e3f-1813-4c94-9343-3ef3c8b4b880",
          "hasValidationError" : false,
          "id" : "pbText"
        } ], [ {
          "type" : "component",
          "dimension" : {
            "xs" : 12
          },
          "propertyValues" : {
            "cssClasses" : {
              "type" : "constant",
              "value" : ""
            },
            "hidden" : {
              "type" : "constant",
              "value" : false
            },
            "readOnly" : {
              "type" : "constant",
              "value" : false
            },
            "required" : {
              "type" : "constant",
              "value" : false
            },
            "minLength" : {
              "type" : "constant",
              "value" : ""
            },
            "maxLength" : {
              "type" : "constant",
              "value" : ""
            },
            "labelHidden" : {
              "type" : "constant",
              "value" : false
            },
            "label" : {
              "type" : "interpolation",
              "value" : "Answer"
            },
            "labelPosition" : {
              "type" : "constant",
              "value" : "top"
            },
            "labelWidth" : {
              "type" : "constant",
              "value" : 1
            },
            "value" : {
              "type" : "variable",
              "value" : "claim.answer"
            }
          },
          "reference" : "876b0577-c04f-4b75-8c78-296e853450c2",
          "hasValidationError" : false,
          "id" : "pbTextarea"
        } ] ]
      } ], [ {
        "type" : "component",
        "dimension" : {
          "xs" : 12
        },
        "propertyValues" : {
          "removeItem" : {
            "type" : "variable"
          },
          "hidden" : {
            "type" : "constant",
            "value" : false
          },
          "cssClasses" : {
            "type" : "constant",
            "value" : ""
          },
          "widgetId" : {
            "type" : "constant",
            "value" : "pbButton"
          },
          "buttonStyle" : {
            "type" : "constant",
            "value" : "primary"
          },
          "readOnly" : {
            "type" : "constant",
            "value" : false
          },
          "label" : {
            "type" : "interpolation",
            "value" : "Submit"
          },
          "dataToSend" : {
            "type" : "expression",
            "value" : "formOutput"
          },
          "dataFromError" : {
            "type" : "variable",
            "value" : "formOutput._submitError"
          },
          "labelHidden" : {
            "type" : "constant",
            "value" : false
          },
          "collectionPosition" : {
            "type" : "constant"
          },
          "targetUrlOnSuccess" : {
            "type" : "interpolation",
            "value" : "/bonita"
          },
          "action" : {
            "type" : "constant",
            "value" : "Submit task"
          },
          "collectionToModify" : {
            "type" : "variable"
          },
          "valueToAdd" : {
            "type" : "expression"
          },
          "disabled" : {
            "type" : "expression",
            "value" : "$form.$invalid"
          },
          "alignment" : {
            "type" : "constant",
            "value" : "center"
          },
          "class" : {
            "type" : "constant",
            "value" : "org.bonitasoft.web.designer.experimental.parametrizedWidget.ButtonWidget"
          },
          "dimension" : {
            "type" : "constant",
            "value" : 12
          }
        },
        "reference" : "a9b28adb-48a5-49a6-a4d4-63861c3d3565",
        "hasValidationError" : false,
        "id" : "pbButton"
      } ], [ {
        "type" : "component",
        "dimension" : {
          "xs" : 12
        },
        "propertyValues" : {
          "allowHTML" : {
            "type" : "constant",
            "value" : true
          },
          "labelHidden" : {
            "type" : "constant",
            "value" : true
          },
          "hidden" : {
            "type" : "expression",
            "value" : "!formOutput._submitError.message"
          },
          "cssClasses" : {
            "type" : "constant",
            "value" : "alert alert-danger col-lg-6 col-lg-offset-3"
          },
          "widgetId" : {
            "type" : "constant",
            "value" : "pbText"
          },
          "readOnly" : {
            "type" : "constant",
            "value" : false
          },
          "label" : {
            "type" : "interpolation"
          },
          "text" : {
            "type" : "interpolation",
            "value" : "<strong>Debug message</strong>\n<br/>\n{{formOutput._submitError.message}}\n{{submit_errors_list}}"
          },
          "alignment" : {
            "type" : "constant",
            "value" : "left"
          },
          "class" : {
            "type" : "constant",
            "value" : "org.bonitasoft.web.designer.experimental.parametrizedWidget.TextWidget"
          },
          "dimension" : {
            "type" : "constant",
            "value" : 12
          }
        },
        "reference" : "726e1eba-6b96-401a-bcb7-d3814ae83013",
        "hasValidationError" : false,
        "id" : "pbText"
      } ] ]
    }
  } ] ],
  "assets" : [ {
    "id" : "aeb3ddd7-1c86-4a00-8df3-2cd69c6018b8",
    "name" : "style.css",
    "type" : "css",
    "order" : 0,
    "external" : false
  } ],
  "inactiveAssets" : [ ],
  "data" : {
    "task" : {
      "type" : "url",
      "value" : "../API/bpm/userTask/{{taskId}}",
      "exposed" : false
    },
    "submit_errors_list" : {
      "type" : "expression",
      "value" : "if($data.formOutput && $data.formOutput._submitError && $data.formOutput._submitError.explanations){\n\tconst liElements = $data.formOutput._submitError.explanations\n\t\t.filter(cause => cause !== null)\n\t\t.map(cause => \"<li>\" + cause + \"</li>\")\n\t\t.join('');\n\tif(liElements){\n\t\treturn \"<ul>\" + liElements + \"</ul>\";\n\t}\n}",
      "exposed" : false
    },
    "formOutput" : {
      "type" : "expression",
      "value" : "if( $data.claim ){\n\treturn {\n\t\t//map claim variable to expected task contract input\n\t\tclaimInput: {\n\t\t\tanswer: $data.claim.answer !== undefined ? $data.claim.answer : null\n\t\t}\n\t}\n}",
      "exposed" : false
    },
    "context" : {
      "type" : "url",
      "value" : "../API/bpm/userTask/{{taskId}}/context",
      "exposed" : false
    },
    "claim" : {
      "type" : "url",
      "value" : "../{{context.claim_ref.link}}",
      "exposed" : false
    },
    "taskId" : {
      "type" : "urlparameter",
      "value" : "id",
      "exposed" : false
    }
  },
  "hasValidationError" : false,
  "uuid" : "2ec9255b-1a3b-46fd-82a3-03bd7ab8d712",
  "type" : "form",
  "description" : "Page generated with Bonita UI designer"
}